hatch_buildext/__about__.py
hatch_buildext/__init__.py
hatch_buildext/_compat.py
hatch_buildext/_types.py
hatch_buildext/_utils.py
hatch_buildext/hooks.py
hatch_buildext/plugin.py
hatch_buildext/py.typed
hatch_buildext/core/__init__.py
hatch_buildext/core/macro.py
hatch_buildext/core/resolver.py
hatch_buildext-0.2.0.dist-info/METADATA
hatch_buildext-0.2.0.dist-info/WHEEL
hatch_buildext-0.2.0.dist-info/entry_points.txt
hatch_buildext-0.2.0.dist-info/licenses/LICENSE.txt
hatch_buildext-0.2.0.dist-info/RECORD
