Metadata-Version: 2.4
Name: hatch-buildext
Version: 0.2.0
Project-URL: Documentation, https://github.com/xoudini/hatch-buildext#readme
Project-URL: Issues, https://github.com/xoudini/hatch-buildext/issues
Project-URL: Source, https://github.com/xoudini/hatch-buildext
License-Expression: Apache-2.0
License-File: LICENSE.txt
Keywords: build,extension modules,hatch,packaging
Classifier: Development Status :: 4 - Beta
Classifier: Programming Language :: Python
Classifier: Programming Language :: Python :: 3.8
Classifier: Programming Language :: Python :: 3.9
Classifier: Programming Language :: Python :: 3.10
Classifier: Programming Language :: Python :: 3.11
Classifier: Programming Language :: Python :: 3.12
Classifier: Programming Language :: Python :: 3.13
Classifier: Programming Language :: Python :: Implementation :: CPython
Classifier: Programming Language :: Python :: Implementation :: PyPy
Classifier: Topic :: Software Development :: Build Tools
Classifier: Topic :: Software Development :: Code Generators
Classifier: Topic :: Software Development :: Compilers
Requires-Python: >=3.8
Requires-Dist: hatchling
Requires-Dist: setuptools
